pytest_splinter/__init__.py
pytest_splinter/plugin.py
pytest_splinter/splinter_patches.py
pytest_splinter/webdriver_patches.py
pytest_splinter/profiles/firefox/.marker
pytest_splinter-3.3.2.dist-info/AUTHORS.rst
pytest_splinter-3.3.2.dist-info/LICENSE.txt
pytest_splinter-3.3.2.dist-info/METADATA
pytest_splinter-3.3.2.dist-info/WHEEL
pytest_splinter-3.3.2.dist-info/entry_points.txt
pytest_splinter-3.3.2.dist-info/top_level.txt
pytest_splinter-3.3.2.dist-info/RECORD
