Metadata-Version: 2.1
Name: pytest-splinter
Version: 3.3.2
Summary: Splinter plugin for pytest testing framework
Home-page: https://github.com/pytest-dev/pytest-splinter
Author: Anatoly Bubenkov, Paylogic International and others
Author-email: bubenkoff@gmail.com
License: MIT license
Project-URL: Bug Tracker, https://github.com/pytest-dev/pytest-splinter/issues
Project-URL: Changes, https://github.com/pytest-dev/pytest-splinter/blob/master/CHANGES.rst
Project-URL: Documentation, https://github.com/pytest-dev/pytest-splinter/blob/master/README.rst
Project-URL: Source Code, https://github.com/pytest-dev/pytest-splinter
Classifier: Development Status :: 6 - Mature
Classifier: Intended Audience :: Developers
Classifier: License :: OSI Approved :: MIT License
Classifier: Operating System :: POSIX
Classifier: Operating System :: Microsoft :: Windows
Classifier: Operating System :: MacOS :: MacOS X
Classifier: Topic :: Software Development :: Testing
Classifier: Topic :: Software Development :: Libraries
Classifier: Topic :: Utilities
Classifier: Programming Language :: Python :: 3
Classifier: Programming Language :: Python :: 3.6
Classifier: Programming Language :: Python :: 3.7
Classifier: Programming Language :: Python :: 3.8
License-File: LICENSE.txt
License-File: AUTHORS.rst
